ascend_io_cli/__init__.py
ascend_io_cli/cli.py
ascend_io_cli/commands/__init__.py
ascend_io_cli/commands/apply.py
ascend_io_cli/commands/build.py
ascend_io_cli/commands/clone.py
ascend_io_cli/commands/config.py
ascend_io_cli/commands/create.py
ascend_io_cli/commands/delete.py
ascend_io_cli/commands/describe.py
ascend_io_cli/commands/download.py
ascend_io_cli/commands/find.py
ascend_io_cli/commands/list.py
ascend_io_cli/commands/pause.py
ascend_io_cli/commands/refresh.py
ascend_io_cli/commands/reset.py
ascend_io_cli/commands/resume.py
ascend_io_cli/commands/support/lineage_support.py
ascend_io_cli/commands/utils.py
ascend_io_cli/commands/utils_commands/migration.py
ascend_io_cli/commands/utils_commands/migration_support.py
ascend_io_cli/commands/version.py
ascend_io_cli/support.py
ascend_io_cli-1.0.18.dist-info/LICENSE
ascend_io_cli-1.0.18.dist-info/METADATA
ascend_io_cli-1.0.18.dist-info/WHEEL
ascend_io_cli-1.0.18.dist-info/entry_points.txt
ascend_io_cli-1.0.18.dist-info/RECORD
