Metadata-Version: 2.1
Name: ascend-io-cli
Version: 1.0.18
Summary: The Ascend CLI
Home-page: https://www.ascend.io
License: Apache-2.0
Keywords: ascend,pipeline,data,automation,platform
Author: Ascend.io Engineering
Author-email: support@ascend.io
Maintainer: Ascend.io Engineering
Maintainer-email: support@ascend.io
Requires-Python: >=3.9,<4.0
Classifier: Intended Audience :: Developers
Classifier: License :: OSI Approved :: Apache Software License
Classifier: Programming Language :: Python :: 3
Classifier: Programming Language :: Python :: 3.9
Classifier: Programming Language :: Python :: 3.10
Classifier: Programming Language :: Python :: 3.11
Classifier: Programming Language :: Python :: 3 :: Only
Classifier: Topic :: Software Development :: Build Tools
Classifier: Topic :: Software Development :: Libraries :: Python Modules
Requires-Dist: PyYAML (>=6.0,<7.0)
Requires-Dist: ascend-io-sdk (>=0.2.62,<0.3.0)
Requires-Dist: jsonpath-ng (>=1.6.1,<2.0.0)
Requires-Dist: pipdeptree (>=2.12.0,<3.0.0)
Requires-Dist: rich (>=13,<14)
Requires-Dist: shellingham (==1.5.4)
Requires-Dist: tabulate (>=0.9.0,<0.10.0)
Requires-Dist: tomlkit (>=0.12.1,<0.13.0)
Requires-Dist: typer[all] (>=0.9.0,<0.10.0)
Project-URL: Ascend.io, https://www.ascend.io
Project-URL: Ascend Developer Hub, https://developer.ascend.io
Project-URL: Documentation, https://developer.ascend.io
